hippogryph/__about__.py
hippogryph/__init__.py
hippogryph/__main__.py
hippogryph/cases.py
hippogryph/grid.py
hippogryph/meshblock.py
hippogryph/utils.py
hippogryph/cli/__init__.py
hippogryph/exodusii/__init__.py
hippogryph/exodusii/allclose.py
hippogryph/exodusii/config.py
hippogryph/exodusii/copy.py
hippogryph/exodusii/element.py
hippogryph/exodusii/ex_params.py
hippogryph/exodusii/exodus_h.py
hippogryph/exodusii/exoread.py
hippogryph/exodusii/extension.py
hippogryph/exodusii/file.py
hippogryph/exodusii/find_in_region.py
hippogryph/exodusii/lineout.py
hippogryph/exodusii/nc.py
hippogryph/exodusii/netcdf.py
hippogryph/exodusii/parallel_file.py
hippogryph/exodusii/put_solution.py
hippogryph/exodusii/region.py
hippogryph/exodusii/similar.py
hippogryph/exodusii/util.py
hippogryph/plot3d/LICENSE
hippogryph/plot3d/__init__.py
hippogryph/plot3d/block.py
hippogryph/plot3d/blockfunctions.py
hippogryph/plot3d/connectivity.py
hippogryph/plot3d/differencing.py
hippogryph/plot3d/face.py
hippogryph/plot3d/facefunctions.py
hippogryph/plot3d/listfunctions.py
hippogryph/plot3d/periodicity.py
hippogryph/plot3d/point_match.py
hippogryph/plot3d/read.py
hippogryph/plot3d/split_block.py
hippogryph/plot3d/write.py
hippogryph-0.2.0.dist-info/METADATA
hippogryph-0.2.0.dist-info/WHEEL
hippogryph-0.2.0.dist-info/entry_points.txt
hippogryph-0.2.0.dist-info/licenses/LICENSE.txt
hippogryph-0.2.0.dist-info/RECORD
