Metadata-Version: 2.4
Name: hippogryph
Version: 0.2.0
Summary: Multiblock structured mesh generation with Python
Project-URL: Documentation, https://github.com/jasondegraw/hippogryph#readme
Project-URL: Issues, https://github.com/jasondegraw/hippogryph/issues
Project-URL: Source, https://github.com/jasondegraw/hippogryph
Author-email: "Jason W. DeGraw" <jason.degraw@gmail.com>
License-Expression: BSD-3-Clause
License-File: LICENSE.txt
Classifier: Development Status :: 4 - Beta
Classifier: Programming Language :: Python
Classifier: Programming Language :: Python :: 3.10
Classifier: Programming Language :: Python :: 3.11
Classifier: Programming Language :: Python :: 3.12
Classifier: Programming Language :: Python :: Implementation :: CPython
Classifier: Programming Language :: Python :: Implementation :: PyPy
Requires-Python: >=3.10
Requires-Dist: click
Requires-Dist: netcdf4
Requires-Dist: numpy
Requires-Dist: pandas
